distributions_probmax/Binomialdistribution.py
distributions_probmax/Gaussiandistribution.py
distributions_probmax/Generaldistribution.py
distributions_probmax/__init__.py
distributions_probmax-0.1.dist-info/METADATA
distributions_probmax-0.1.dist-info/WHEEL
distributions_probmax-0.1.dist-info/top_level.txt
distributions_probmax-0.1.dist-info/RECORD
